TextEdit/Sound.py
TextEdit/__init__.py
TextEdit/defile.py
TextEdit/defileSound.py
TextEdit/sound/espace.wav
TextEdit/sound/lettre.wav
TextEdit/sound/point.wav
TextEdit-1.4.dist-info/LICENSE
TextEdit-1.4.dist-info/METADATA
TextEdit-1.4.dist-info/WHEEL
TextEdit-1.4.dist-info/top_level.txt
TextEdit-1.4.dist-info/RECORD
