Metadata-Version: 2.1
Name: TextEdit
Version: 1.4
Summary: A small module for to display the letters at the sequence.
Home-page: https://github.com/C0rent1Perdry/TextEdit-1.4
Author: Corentin Perdry
Author-email: corentin.perdry@gmail.com
License: UNKNOWN
Project-URL: Bug Tracker, https://github.com/C0rent1Perdry/TextEdit-1.4/issues
Platform: UNKNOWN
Classifier: Programming Language :: Python :: 3
Classifier: License :: OSI Approved :: MIT License
Classifier: Operating System :: OS Independent
Requires-Python: >=3.6
License-File: LICENSE
